<?xml version="1.0" ?>
<ships>
	<awing actions="TARGET_LOCK + BOOST + FOCUS + EVADE" image="img/awing.png" name="A-Wing" faction="rebel">
		<simple>
			<maneuver>F2</maneuver>
			<maneuver>F3</maneuver>
			<maneuver>F4</maneuver>
			<maneuver>F5</maneuver>
			<maneuver>TL2</maneuver>
			<maneuver>BL2</maneuver>
			<maneuver>BR2</maneuver>
			<maneuver>TR2</maneuver>
		</simple>
		<normal>
			<maneuver>TL1</maneuver>
			<maneuver>TL3</maneuver>
			<maneuver>BL3</maneuver>
			<maneuver>BR3</maneuver>
			<maneuver>TR1</maneuver>
			<maneuver>TR3</maneuver>
		</normal>
		<difficult>
			<maneuver>K3</maneuver>
			<maneuver>K5</maneuver>
		</difficult>
	</awing>
	<bwing actions="BARREL_ROLL + FOCUS + TARGET_LOCK" image="img/bwing.png" name="B-Wing" faction="rebel">
		<simple>
			<maneuver>BL1</maneuver>
			<maneuver>F1</maneuver>
			<maneuver>F2</maneuver>
			<maneuver>BR1</maneuver>
		</simple>
		<normal>
			<maneuver>TL2</maneuver>
			<maneuver>BL2</maneuver>
			<maneuver>F3</maneuver>
			<maneuver>BR2</maneuver>
			<maneuver>TR2</maneuver>
		</normal>
		<difficult>
			<maneuver>TL1</maneuver>
			<maneuver>BL3</maneuver>
			<maneuver>F4</maneuver>
			<maneuver>BR3</maneuver>
			<maneuver>TR1</maneuver>
			<maneuver>K2</maneuver>
		</difficult>
	</bwing>
	<corvette actions="CORDINATE + RECOVER + REINFORCE + TARGET_LOCK" image="img/corvette.png" name="CR90 Corvette" faction="rebel">
		<simple>
		</simple>
		<normal>
		</normal>
		<difficult>
		</difficult>
	</corvette>
	<ewing actions="BARREL_ROLL + EVADE + FOCUS + TARGET_LOCK" image="img/ewing.png" name="E-Wing" faction="rebel">
		<simple>
		</simple>
		<normal>
		</normal>
		<difficult>
		</difficult>
	</ewing>
	<falcon actions="TARGET_LOCK + FOCUS" image="img/falcon.png" name="YT-1300" faction="rebel">
		<simple>
			<maneuver>F1</maneuver>
			<maneuver>F2</maneuver>
			<maneuver>BL1</maneuver>
			<maneuver>BR1</maneuver>
		</simple>
		<normal>
			<maneuver>TL1</maneuver>
			<maneuver>TL2</maneuver>
			<maneuver>BL2</maneuver>
			<maneuver>BL3</maneuver>
			<maneuver>F3</maneuver>
			<maneuver>F4</maneuver>
			<maneuver>BR2</maneuver>
			<maneuver>BR3</maneuver>
			<maneuver>TR1</maneuver>
			<maneuver>TR2</maneuver>
		</normal>
		<difficult>
			<maneuver>K3</maneuver>
			<maneuver>K4</maneuver>
		</difficult>
	</falcon>
	<hwk290 actions="FOCUS + TARGET_LOCK" image="img/hwk290.png" name="HWK-290" faction="rebel">
		<simple>
			<maneuver>BL1</maneuver>
			<maneuver>F1</maneuver>
			<maneuver>F2</maneuver>
			<maneuver>BR1</maneuver>
		</simple>
		<normal>
			<maneuver>TL2</maneuver>
			<maneuver>BL2</maneuver>
			<maneuver>F3</maneuver>
			<maneuver>BR2</maneuver>
			<maneuver>TR2</maneuver>
		</normal>
		<difficult>
			<maneuver>BL3</maneuver>
			<maneuver>F4</maneuver>
			<maneuver>BR3</maneuver>
		</difficult>
	</hwk290>
	<lambda actions="FOCUS + TARGET_LOCK" image="img/lambda.png" name="Lambda Shuttle" faction="empire">
		<simple>
			<maneuver>BL1</maneuver>
			<maneuver>F1</maneuver>
			<maneuver>F2</maneuver>
			<maneuver>BR1</maneuver>
		</simple>
		<normal>
			<maneuver>BL2</maneuver>
			<maneuver>F3</maneuver>
			<maneuver>BR2</maneuver>
		</normal>
		<difficult>
			<maneuver>TL2</maneuver>
			<maneuver>BL3</maneuver>
			<maneuver>F0</maneuver>
			<maneuver>BR3</maneuver>
			<maneuver>TR2</maneuver>
		</difficult>
	</lambda>
	<slave1 actions="TARGET_LOCK + FOCUS + EVADE" image="img/slave1.png" name="Firespray-31" faction="empire">
		<simple>
			<maneuver>F1</maneuver>
			<maneuver>F2</maneuver>
			<maneuver>BL1</maneuver>
			<maneuver>BR1</maneuver>
		</simple>
		<normal>
			<maneuver>TL2</maneuver>
			<maneuver>TL3</maneuver>
			<maneuver>BL2</maneuver>
			<maneuver>BL3</maneuver>
			<maneuver>F3</maneuver>
			<maneuver>F4</maneuver>
			<maneuver>BR2</maneuver>
			<maneuver>BR3</maneuver>
			<maneuver>TR2</maneuver>
			<maneuver>TR3</maneuver>
		</normal>
		<difficult>
			<maneuver>K3</maneuver>
			<maneuver>K4</maneuver>
		</difficult>
	</slave1>
	<tie actions="BARREL_ROLL + FOCUS + EVADE" image="img/tie.png" name="Tie Fighter" faction="empire">
		<simple>
			<maneuver>F2</maneuver>
			<maneuver>BL2</maneuver>
			<maneuver>BR2</maneuver>
			<maneuver>F3</maneuver>
		</simple>
		<normal>
			<maneuver>TL1</maneuver>
			<maneuver>TL2</maneuver>
			<maneuver>TL3</maneuver>
			<maneuver>BL3</maneuver>
			<maneuver>F4</maneuver>
			<maneuver>F5</maneuver>
			<maneuver>BR3</maneuver>
			<maneuver>TR1</maneuver>
			<maneuver>TR2</maneuver>
			<maneuver>TR3</maneuver>
		</normal>
		<difficult>
			<maneuver>K3</maneuver>
			<maneuver>K4</maneuver>
		</difficult>
	</tie>
	<tieAdvanced actions="TARGET_LOCK + BARREL_ROLL + FOCUS + EVADE" image="img/TieAdvanced.png" name="Tie Advanced" faction="empire">
		<simple>
			<maneuver>BL1</maneuver>
			<maneuver>BR1</maneuver>
			<maneuver>F2</maneuver>
			<maneuver>F3</maneuver>
		</simple>
		<normal>
			<maneuver>TL2</maneuver>
			<maneuver>TL3</maneuver>
			<maneuver>BL2</maneuver>
			<maneuver>BL3</maneuver>
			<maneuver>F4</maneuver>
			<maneuver>F5</maneuver>
			<maneuver>BR2</maneuver>
			<maneuver>BR3</maneuver>
			<maneuver>TR2</maneuver>
			<maneuver>TR3</maneuver>
		</normal>
		<difficult>
			<maneuver>K4</maneuver>
		</difficult>
	</tieAdvanced>
	<tieBomber actions="BARREL_ROLL + FOCUS + TARGET_LOCK" image="img/tieBomber.png" name="Tie Bomber" faction="empire">
		<simple>
			<maneuver>F1</maneuver>
			<maneuver>F2</maneuver>
			<maneuver>F3</maneuver>
			<maneuver>BL2</maneuver>
			<maneuver>BR2</maneuver>
		</simple>
		<normal>
			<maneuver>BL1</maneuver>
			<maneuver>TL3</maneuver>
			<maneuver>BL3</maneuver>
			<maneuver>F4</maneuver>
			<maneuver>BR3</maneuver>
			<maneuver>BL3</maneuver>
			<maneuver>BR1</maneuver>
		</normal>
		<difficult>
			<maneuver>TL2</maneuver>
			<maneuver>TR2</maneuver>
			<maneuver>K5</maneuver>
		</difficult>
	</tieBomber>
	<tieDefender actions="BARREL_ROLL + FOCUS + TARGET_LOCK" image="img/tieDefender.png" name="Tie Defender" faction="empire">
		<simple>
		</simple>
		<normal>
		</normal>
		<difficult>
		</difficult>
	</tieDefender>
	<tieInterceptor actions="BARREL_ROLL + BOOST + FOCUS + EVADE" image="img/tieInterceptor.png" name="Tie Interceptor" faction="empire">
		<simple>
			<maneuver>F2</maneuver>
			<maneuver>F3</maneuver>
			<maneuver>F4</maneuver>
			<maneuver>TL2</maneuver>
			<maneuver>BL2</maneuver>
			<maneuver>BR2</maneuver>
			<maneuver>TR2</maneuver>
		</simple>
		<normal>
			<maneuver>TL1</maneuver>
			<maneuver>TL3</maneuver>
			<maneuver>BL3</maneuver>
			<maneuver>F5</maneuver>
			<maneuver>BR3</maneuver>
			<maneuver>TR1</maneuver>
			<maneuver>TR3</maneuver>
		</normal>
		<difficult>
			<maneuver>K3</maneuver>
			<maneuver>K5</maneuver>
		</difficult>
	</tieInterceptor>
	<tiePhantom actions="BARREL_ROLL + CLOAKING + EVADE + FOCUS" image="img/tiePhantom.png" name="Tie Phantom" faction="empire">
		<simple>
		</simple>
		<normal>
		</normal>
		<difficult>
		</difficult>
	</tiePhantom>
	<transport actions="CORDINATE + JAM + RECOVER + REINFORCE" image="img/transport.png" name="Rebel Transport" faction="rebel">
		<simple>
		</simple>
		<normal>
		</normal>
		<difficult>
		</difficult>
	</transport>
	<xwing actions="TARGET_LOCK + FOCUS" image="img/xwing.png" name="X-Wing" faction="rebel">
		<simple>
			<maneuver>F1</maneuver>
			<maneuver>BL1</maneuver>
			<maneuver>BR1</maneuver>
			<maneuver>F2</maneuver>
		</simple>
		<normal>
			<maneuver>TL2</maneuver>
			<maneuver>TL3</maneuver>
			<maneuver>BL2</maneuver>
			<maneuver>BL3</maneuver>
			<maneuver>F3</maneuver>
			<maneuver>F4</maneuver>
			<maneuver>BR2</maneuver>
			<maneuver>BR3</maneuver>
			<maneuver>TR2</maneuver>
			<maneuver>TR3</maneuver>
		</normal>
		<difficult>
			<maneuver>K4</maneuver>
		</difficult>
	</xwing>
	<ywing actions="TARGET_LOCK + FOCUS" image="img/ywing.png" name="Y-Wing" faction="rebel">
		<simple>
			<maneuver>F1</maneuver>
			<maneuver>F2</maneuver>
		</simple>
		<normal>
			<maneuver>TL2</maneuver>
			<maneuver>BL1</maneuver>
			<maneuver>BL2</maneuver>
			<maneuver>BL3</maneuver>
			<maneuver>F3</maneuver>
			<maneuver>BR1</maneuver>
			<maneuver>BR2</maneuver>
			<maneuver>BR3</maneuver>
			<maneuver>TR2</maneuver>
		</normal>
		<difficult>
			<maneuver>TL3</maneuver>
			<maneuver>TR3</maneuver>
			<maneuver>F4</maneuver>
			<maneuver>K4</maneuver>
		</difficult>
	</ywing>
	<z95 actions="FOCUS + TARGET_LOCK" image="img/z95.png" name="Z-95 Headhunter" faction="rebel">
		<simple>
		</simple>
		<normal>
		</normal>
		<difficult>
		</difficult>
	</z95>
</ships>
